{
  "bookings": [
    {
      "id": 1,
      "customer": "Rahul",
      "sport": "Football",
      "hours": 2,
      "amount": 2400,
      "status": "Confirmed"
    },
    {
      "id": 2,
      "customer": "Priya",
      "sport": "Cricket",
      "hours": 3,
      "amount": 3600,
      "status": "Pending"
    },
    {
      "id": 3,
      "customer": "Arun",
      "sport": "Football",
      "hours": 1,
      "amount": 1200,
      "status": "Confirmed"
    },
    {
      "id": 4,
      "customer": "Priya",
      "sport": "Cricket",
      "hours": 3,
      "amount": 3600,
      "status": "Pending"
    },
    {
      "id": 5,
      "customer": "Rahul",
      "sport": "Football",
      "hours": 2,
      "amount": 2400,
      "status": "Confirmed"
    }
  ]
}